editconfig/__init__.py
editconfig-0.1.2.dist-info/METADATA
editconfig-0.1.2.dist-info/WHEEL
editconfig-0.1.2.dist-info/entry_points.txt
editconfig-0.1.2.dist-info/top_level.txt
editconfig-0.1.2.dist-info/RECORD
